mini/__init__.py
mini/admin.py
mini/apps.py
mini/models.py
mini/tests.py
mini/urls.py
mini/views.py
mini/migrations/__init__.py
mini/static/__init__.py
mini/static/mini/__init__.py
mini/static/mini/css/__init__.py
mini/static/mini/css/rte_theme_default.css
mini/static/mini/js/__init__.py
mini/static/mini/js/rte.js
mini/static/mini/plugins/-combine-plugin.txt
mini/static/mini/plugins/__init__.py
mini/static/mini/plugins/all_plugins.js
mini/static/mini/plugins/html2pdf.js
mini/static/mini/plugins/imageeditor.js
mini/static/mini/plugins/insertcode.js
mini/static/mini/plugins/insertemoji.js
mini/static/mini/plugins/insertgallery.js
mini/static/mini/plugins/inserttemplate.js
mini/static/mini/plugins/samples/insertcode_v1.js
mini/static/mini/plugins/tui.image-editor/fabric.min.js
mini/static/mini/plugins/tui.image-editor/note.txt
mini/static/mini/plugins/tui.image-editor/tui-code-snippet.min.js
mini/static/mini/plugins/tui.image-editor/tui-color-picker.min.css
mini/static/mini/plugins/tui.image-editor/tui-color-picker.min.js
mini/static/mini/plugins/tui.image-editor/tui-image-editor.min.css
mini/static/mini/plugins/tui.image-editor/tui-image-editor.min.js
mini/static/mini/plugins/tui.image-editor/svg/icon-a.svg
mini/static/mini/plugins/tui.image-editor/svg/icon-b.svg
mini/static/mini/plugins/tui.image-editor/svg/icon-c.svg
mini/static/mini/plugins/tui.image-editor/svg/icon-d.svg
mini/static/mini/runtime/__init__.py
mini/static/mini/runtime/colorpicker_more_ns.htm
mini/static/mini/runtime/help.htm
mini/static/mini/runtime/richtexteditor_content.css
mini/static/mini/runtime/richtexteditor_preview.css
mini/static/mini/runtime/richtexteditor_preview.js
mini/static/mini/runtime/images/1x1.gif
mini/static/mini/runtime/images/cpie_Color.cur
mini/static/mini/runtime/images/cpie_GradientPositionDark.gif
mini/static/mini/runtime/images/cpie_GradientPositionLight.gif
mini/static/mini/runtime/images/cpie_VerticalPosition.gif
mini/static/mini/runtime/images/cpie_WebSafe.gif
django_mini_ui-0.0.2.dist-info/LICENSE
django_mini_ui-0.0.2.dist-info/METADATA
django_mini_ui-0.0.2.dist-info/WHEEL
django_mini_ui-0.0.2.dist-info/top_level.txt
django_mini_ui-0.0.2.dist-info/RECORD
