Metadata-Version: 2.1
Name: django-mini-ui
Version: 0.0.2
Summary: A small UI editor for django apps.
Home-page: https://github.com/ranjithsvcetcse/django-mini
Author: Malagundla Ranjith Kumar
Author-email: ranjithsvcetcseb@gmail.com
License: UNKNOWN
Platform: UNKNOWN
Classifier: Programming Language :: Python :: 3
Classifier: Framework :: Django :: 3.0
Classifier: Operating System :: OS Independent
Classifier: Intended Audience :: Developers
Classifier: Natural Language :: English
Classifier: Topic :: Internet :: WWW/HTTP :: Site Management
Requires-Python: >=3.6
Requires-Dist: django (>=3)
